README.md
setup.cfg
setup.py
cordport/__init__.py
cordport/__main__.py
cordport/core.py
cordport.egg-info/PKG-INFO
cordport.egg-info/SOURCES.txt
cordport.egg-info/dependency_links.txt
cordport.egg-info/entry_points.txt
cordport.egg-info/top_level.txt