Metadata-Version: 1.1
Name: cordport
Version: 1.0.0.dev0
Summary: Central Office Re-architecture as Datacenter(CORD) ovs debug tool
Home-page: https://github.com/aweimeow/cordport
Author: Wei-Yu Chen
Author-email: aweimeow.tw@gmail.com
License: MIT
Download-URL: https://github.com/aweimeow/cordport/archive/1.0.tar.gz
Platform: UNKNOWN
